tlvdict/__init__.py
tlvdict-1.2.0.dist-info/LICENSE
tlvdict-1.2.0.dist-info/WHEEL
tlvdict-1.2.0.dist-info/METADATA
tlvdict-1.2.0.dist-info/RECORD
